kerb/__init__.py
kerb-0.1.1.dist-info/licenses/LICENSE
kerb-0.1.1.dist-info/METADATA
kerb-0.1.1.dist-info/WHEEL
kerb-0.1.1.dist-info/top_level.txt
kerb-0.1.1.dist-info/RECORD
