Metadata-Version: 2.4
Name: kerb
Version: 0.1.1
Summary: A toolkit library for developers building LLM applications
Author-email: Wei-Ming Thor <twm_npm@outlook.com>
License: Apache-2.0
Project-URL: Homepage, https://github.com/apxml/kerb
Project-URL: Bug Tracker, https://github.com/apxml/kerb/issues
Project-URL: Documentation, https://github.com/apxml/kerb/docs
Project-URL: Source Code, https://github.com/apxml/kerb
Keywords: llm,ai,machine-learning,nlp,natural-language-processing,toolkit,openai,anthropic,gemini,embeddings,tokenization,generation,evaluation
Classifier: Programming Language :: Python :: 3
Classifier: Programming Language :: Python :: 3.8
Classifier: Programming Language :: Python :: 3.9
Classifier: Programming Language :: Python :: 3.10
Classifier: Programming Language :: Python :: 3.11
Classifier: Programming Language :: Python :: 3.12
Classifier: License :: OSI Approved :: Apache Software License
Classifier: Operating System :: OS Independent
Classifier: Development Status :: 4 - Beta
Classifier: Intended Audience :: Developers
Classifier: Topic :: Software Development :: Libraries :: Python Modules
Classifier: Topic :: Scientific/Engineering :: Artificial Intelligence
Requires-Python: >=3.8
License-File: LICENSE
Provides-Extra: dev
Requires-Dist: pytest>=8.0.0; extra == "dev"
Provides-Extra: tokenizers
Requires-Dist: tiktoken>=0.5.0; extra == "tokenizers"
Requires-Dist: transformers>=4.30.0; extra == "tokenizers"
Provides-Extra: embeddings
Requires-Dist: sentence-transformers>=2.0.0; extra == "embeddings"
Requires-Dist: openai>=1.0.0; extra == "embeddings"
Provides-Extra: generation
Requires-Dist: openai>=1.0.0; extra == "generation"
Requires-Dist: anthropic>=0.18.0; extra == "generation"
Requires-Dist: google-generativeai>=0.3.0; extra == "generation"
Requires-Dist: cohere>=4.0.0; extra == "generation"
Provides-Extra: evaluation
Requires-Dist: rouge-score>=0.1.2; extra == "evaluation"
Requires-Dist: nltk>=3.8.0; extra == "evaluation"
Requires-Dist: bert-score>=0.3.13; extra == "evaluation"
Requires-Dist: sacrebleu>=2.3.0; extra == "evaluation"
Provides-Extra: documents
Requires-Dist: pypdf>=3.0.0; extra == "documents"
Requires-Dist: python-docx>=0.8.11; extra == "documents"
Requires-Dist: requests>=2.28.0; extra == "documents"
Provides-Extra: preprocessing
Requires-Dist: langdetect>=1.0.9; extra == "preprocessing"
Provides-Extra: fine-tuning
Requires-Dist: openai>=1.0.0; extra == "fine-tuning"
Requires-Dist: anthropic>=0.18.0; extra == "fine-tuning"
Requires-Dist: pandas>=2.0.0; extra == "fine-tuning"
Requires-Dist: pyarrow>=12.0.0; extra == "fine-tuning"
Provides-Extra: config
Requires-Dist: cryptography>=41.0.0; extra == "config"
Provides-Extra: all
Requires-Dist: pytest>=8.0.0; extra == "all"
Requires-Dist: tiktoken>=0.5.0; extra == "all"
Requires-Dist: transformers>=4.30.0; extra == "all"
Requires-Dist: sentence-transformers>=2.0.0; extra == "all"
Requires-Dist: openai>=1.0.0; extra == "all"
Requires-Dist: anthropic>=0.18.0; extra == "all"
Requires-Dist: google-generativeai>=0.3.0; extra == "all"
Requires-Dist: cohere>=4.0.0; extra == "all"
Requires-Dist: rouge-score>=0.1.2; extra == "all"
Requires-Dist: nltk>=3.8.0; extra == "all"
Requires-Dist: bert-score>=0.3.13; extra == "all"
Requires-Dist: sacrebleu>=2.3.0; extra == "all"
Requires-Dist: pypdf>=3.0.0; extra == "all"
Requires-Dist: python-docx>=0.8.11; extra == "all"
Requires-Dist: requests>=2.28.0; extra == "all"
Requires-Dist: langdetect>=1.0.9; extra == "all"
Requires-Dist: pandas>=2.0.0; extra == "all"
Requires-Dist: pyarrow>=12.0.0; extra == "all"
Requires-Dist: cryptography>=41.0.0; extra == "all"
Dynamic: license-file
